pylazypdfcore-0.1.0.dist-info/METADATA
pylazypdfcore-0.1.0.dist-info/WHEEL
pylazypdfcore/__init__.py
pylazypdfcore/pylazypdfcore.cpython-311-x86_64-linux-gnu.so
pylazypdfcore-0.1.0.dist-info/RECORD
